df2gspread_ext/__init__.py
df2gspread_ext/_version.py
df2gspread_ext/df2gspread.py
df2gspread_ext/gfiles.py
df2gspread_ext/gspread2df.py
df2gspread_ext/utils.py
gcloud_connectors/__init__.py
gcloud_connectors/bigquery.py
gcloud_connectors/currency_converter.py
gcloud_connectors/ga4.py
gcloud_connectors/ganalytics.py
gcloud_connectors/gdrive.py
gcloud_connectors/gsc.py
gcloud_connectors/gsheets.py
gcloud_connectors/gstorage.py
gcloud_connectors/logger.py
gcloud_connectors/ltv_calculator.py
gcloud_connectors/pd_utils.py
gcloud_connectors-0.2.3.dist-info/METADATA
gcloud_connectors-0.2.3.dist-info/WHEEL
gcloud_connectors-0.2.3.dist-info/top_level.txt
gcloud_connectors-0.2.3.dist-info/RECORD
